setup.py
riakasaurus/__init__.py
riakasaurus/bucket.py
riakasaurus/client.py
riakasaurus/exceptions.py
riakasaurus/mapreduce.py
riakasaurus/metadata.py
riakasaurus/riak.py
riakasaurus/riak_index_entry.py
riakasaurus/riak_object.py
riakasaurus/search.py
riakasaurus.egg-info/PKG-INFO
riakasaurus.egg-info/SOURCES.txt
riakasaurus.egg-info/dependency_links.txt
riakasaurus.egg-info/top_level.txt
riakasaurus/test_crosscompat/__init__.py
riakasaurus/test_crosscompat/test_compat.py
riakasaurus/tests/__init__.py
riakasaurus/tests/test_2i.py
riakasaurus/tests/test_2i_pb.py
riakasaurus/tests/test_basic.py
riakasaurus/tests/test_basic_pb.py
riakasaurus/tests/test_erlmr.py
riakasaurus/tests/test_jsmr.py
riakasaurus/tests/test_objects.py
riakasaurus/tests/test_objects_pb.py
riakasaurus/tests/test_pbc.py
riakasaurus/tests/test_pbc_transport.py
riakasaurus/tests/test_search.py
riakasaurus/transport/__init__.py
riakasaurus/transport/http_transport.py
riakasaurus/transport/pbc_transport.py
riakasaurus/transport/transport.py
riakasaurus/transport/pbc/__init__.py
riakasaurus/transport/pbc/riak_kv_pb2.py
riakasaurus/transport/pbc/riak_pb2.py