Metadata-Version: 1.0
Name: riakasaurus
Version: 1.1.1
Summary: Riakasaurus is a Twisted client library for Riak
Home-page: http://github.com/calston/riakasaurus
Author: Colin Alston
Author-email: colin.alston@gmail.com
License: Apache 2.0
Keywords: twisted riak riakasaurus
Platform: Linux
